LICENSE
README.md
setup.py
src/cit_hio.egg-info/PKG-INFO
src/cit_hio.egg-info/SOURCES.txt
src/cit_hio.egg-info/dependency_links.txt
src/cit_hio.egg-info/entry_points.txt
src/cit_hio.egg-info/not-zip-safe
src/cit_hio.egg-info/requires.txt
src/cit_hio.egg-info/top_level.txt
src/hio/__init__.py
src/hio/__main__.py
src/hio/cli.py
src/hio/daemon.py
src/hio/hioing.py
src/hio/base/__init__.py
src/hio/base/basing.py
src/hio/base/doing.py
src/hio/base/filing.py
src/hio/base/tyming.py
src/hio/core/__init__.py
src/hio/core/coring.py
src/hio/core/wiring.py
src/hio/core/http/__init__.py
src/hio/core/http/clienting.py
src/hio/core/http/httping.py
src/hio/core/http/serving.py
src/hio/core/serial/__init__.py
src/hio/core/serial/serialing.py
src/hio/core/tcp/__init__.py
src/hio/core/tcp/clienting.py
src/hio/core/tcp/serving.py
src/hio/core/tcp/tcping.py
src/hio/core/udp/__init__.py
src/hio/core/udp/udping.py
src/hio/demo/__init__.py
src/hio/demo/web/__init__.py
src/hio/demo/web/demo_web.py
src/hio/demo/web/demoing.py
src/hio/help/__init__.py
src/hio/help/decking.py
src/hio/help/helping.py
src/hio/help/hicting.py
src/hio/help/ogling.py
src/hio/help/timing.py
tests/test_main.py