Metadata-Version: 2.1
Name: cit-hio
Version: 0.6.14
Summary: Hierarchical Concurrency with Async IO
Home-page: https://github.com/ioflo/hio
Author: Samuel M. Smith
Author-email: smith.samuel.m@gmail.com
License: Apache Software License 2.0
Project-URL: Documentation, https://hio.readthedocs.io/
Project-URL: Changelog, https://hio.readthedocs.io/en/latest/changelog.html
Project-URL: Issue Tracker, https://github.com/ProSapien/hio/issues
Keywords: hierarchical concurrency,async io,rich contextual concurrency,structured concurrency
Classifier: Development Status :: 3 - Alpha
Classifier: Intended Audience :: Developers
Classifier: License :: OSI Approved :: Apache Software License
Classifier: Operating System :: Unix
Classifier: Operating System :: POSIX
Classifier: Operating System :: Microsoft :: Windows
Classifier: Programming Language :: Python :: 3.10
Classifier: Programming Language :: Python :: Implementation :: CPython
Classifier: Topic :: Utilities
Requires-Python: >=3.11.6
License-File: LICENSE
Requires-Dist: lmdb>=1.4.1
Requires-Dist: msgpack>=1.0.8
Requires-Dist: cbor2>=5.6.2
Requires-Dist: multidict>=6.0.5
Requires-Dist: falcon>=3.1.3
Requires-Dist: ordered-set>=4.1.0
